Metadata-Version: 2.1
Name: custom-python-matter-server
Version: 6.9.28
Summary: Python Matter WebSocket Server with custom sensors
Author-email: David <davidkuc6@gmail.com>
License: Apache-2.0
Platform: any
Classifier: Development Status :: 3 - Alpha
Classifier: Intended Audience :: Developers
Classifier: Environment :: Console
Classifier: Programming Language :: Python :: 3.11
Classifier: Programming Language :: Python :: 3.12
Classifier: Topic :: Home Automation
Requires-Python: >=3.11
License-File: LICENSE
Requires-Dist: aiohttp
Requires-Dist: aiorun
Requires-Dist: async-timeout
Requires-Dist: coloredlogs
Requires-Dist: orjson
Requires-Dist: home-assistant-chip-clusters==2024.11.3
Provides-Extra: server
Requires-Dist: aiohttp==3.11.7; extra == "server"
Requires-Dist: aiorun==2024.8.1; extra == "server"
Requires-Dist: async-timeout==5.0.1; extra == "server"
Requires-Dist: coloredlogs==15.0.1; extra == "server"
Requires-Dist: cryptography==43.0.3; extra == "server"
Requires-Dist: orjson==3.10.12; extra == "server"
Requires-Dist: zeroconf==0.136.2; extra == "server"
Requires-Dist: home-assistant-chip-core==2024.11.3; extra == "server"
Provides-Extra: test
Requires-Dist: aioresponses==0.7.7; extra == "test"
Requires-Dist: codespell==2.3.0; extra == "test"
Requires-Dist: isort==5.13.2; extra == "test"
Requires-Dist: mypy==1.13.0; extra == "test"
Requires-Dist: pre-commit==4.0.1; extra == "test"
Requires-Dist: pre-commit-hooks==5.0.0; extra == "test"
Requires-Dist: pylint==3.3.1; extra == "test"
Requires-Dist: pytest==8.3.3; extra == "test"
Requires-Dist: pytest-asyncio==0.24.0; extra == "test"
Requires-Dist: pytest-aiohttp==1.0.5; extra == "test"
Requires-Dist: pytest-cov==6.0.0; extra == "test"
Requires-Dist: ruff==0.8.0; extra == "test"
Requires-Dist: tomli==2.1.0; extra == "test"
